ur_lstm/__init__.py
ur_lstm/ur_lstm.py
ur_lstm_torch-0.0.2.dist-info/LICENSE
ur_lstm_torch-0.0.2.dist-info/METADATA
ur_lstm_torch-0.0.2.dist-info/WHEEL
ur_lstm_torch-0.0.2.dist-info/top_level.txt
ur_lstm_torch-0.0.2.dist-info/RECORD
