Metadata-Version: 2.1
Name: ur-lstm-torch
Version: 0.0.2
Summary: Unofficial UR-LSTM implementation in Pytorch
Home-page: https://github.com/r0mainK/ur-lstm
Author: Romain Keramitas
Author-email: r.keramitas@gmail.com
License: MIT
Project-URL: Bug Tracker, https://github.com/r0mainK/ur-lstm/issues
Keywords: ur-lstm,pytorch
Platform: UNKNOWN
Classifier: Development Status :: 3 - Alpha
Classifier: Intended Audience :: Developers
Classifier: Intended Audience :: Science/Research
Classifier: License :: OSI Approved :: MIT License
Classifier: Operating System :: OS Independent
Classifier: Programming Language :: Python :: 3
Classifier: Programming Language :: Python :: 3.6
Classifier: Programming Language :: Python :: 3.7
Classifier: Programming Language :: Python :: 3.8
Classifier: Topic :: Scientific/Engineering :: Artificial Intelligence
Requires-Python: >=3.6
Requires-Dist: torch (<2,>=1.0)
